hussh-0.1.9.dist-info/METADATA
hussh-0.1.9.dist-info/WHEEL
hussh-0.1.9.dist-info/licenses/LICENSE
hussh/__init__.py
hussh/hussh.pypy310-pp73-x86-linux-gnu.so
hussh-0.1.9.dist-info/RECORD
