Metadata-Version: 2.4
Name: hussh
Version: 0.1.9
Classifier: Programming Language :: Rust
Classifier: Programming Language :: Python :: Implementation :: CPython
Classifier: Programming Language :: Python :: Implementation :: PyPy
Classifier: Natural Language :: English
Classifier: Programming Language :: Python :: 3
Classifier: Programming Language :: Python :: 3.8
Classifier: Programming Language :: Python :: 3.9
Classifier: Programming Language :: Python :: 3.10
Classifier: Programming Language :: Python :: 3.11
Classifier: Programming Language :: Python :: 3.12
Classifier: Programming Language :: Python :: 3.13
Classifier: Programming Language :: Python :: 3.14
Classifier: Topic :: System :: Shells
Classifier: Topic :: System :: Networking
Classifier: Topic :: Software Development :: Libraries
Classifier: Topic :: Software Development :: Libraries :: Python Modules
Classifier: Operating System :: POSIX
Classifier: Operating System :: POSIX :: Linux
Classifier: Operating System :: MacOS :: MacOS X
Requires-Dist: docker ; extra == 'dev'
Requires-Dist: maturin ; extra == 'dev'
Requires-Dist: patchelf ; sys_platform == 'linux' and extra == 'dev'
Requires-Dist: pexpect ; extra == 'dev'
Requires-Dist: pre-commit ; extra == 'dev'
Requires-Dist: pytest ; extra == 'dev'
Requires-Dist: pytest-randomly ; extra == 'dev'
Requires-Dist: ruff ; extra == 'dev'
Provides-Extra: dev
License-File: LICENSE
Summary: SSH for Humans
Keywords: ssh,ssh2,rust,pyo3
Author-email: Jacob J Callahan <jacob.callahan05@gmail.com>
Requires-Python: >=3.8
